{
    "BodyParts": {
        "Chest": {
            "Health": {
                "Current": 320,
                "Maximum": 320
            }
        },
      "Head": {
            "Health": {
              "Current": 100,
              "Maximum": 100
            }
        },
        "LeftArm": {
            "Health": {
                "Current": 130,
                "Maximum": 130
            }
        },
        "LeftLeg": {
            "Health": {
                "Current": 140,
                "Maximum": 140
            }
        },
      "RightArm": {
        "Health": {
          "Current": 130,
          "Maximum": 130
        }
      },
        "RightLeg": {
            "Health": {
                "Current": 140,
                "Maximum": 140
            }
        },
      "Stomach": {
        "Health": {
          "Current": 260,
          "Maximum": 260
        }
      }
    }
}
