{
    "BodyParts": {
        "Chest": {
            "Health": {
                "Current": 180,
                "Maximum": 180
            }
        },
      "Head": {
            "Health": {
              "Current": 40,
              "Maximum": 40
            }
        },
        "LeftArm": {
            "Health": {
                "Current": 105,
                "Maximum": 105
            }
        },
        "LeftLeg": {
          "Health": {
            "Current": 110,
            "Maximum": 110
          }
        },
      "RightArm": {
            "Health": {
                "Current": 105,
                "Maximum": 105
            }
        },
        "RightLeg": {
            "Health": {
              "Current": 110,
              "Maximum": 110
            }
        },
      "Stomach": {
        "Health": {
          "Current": 130,
          "Maximum": 130
        }
      }
    }
}
